{
  "name": "Сокровищница Ауры",
  "icon": "naturesaura:aura_trove",
  "category": "naturesaura:items",
  "advancement": "naturesaura:sky_ingot",
  "pages": [
    {
      "type": "text",
      "text": "Когда требуемое количество $(aura) становится слишком большим для хранения в $(l:items/aura_cache)Кэше Ауры$() без необходимости слишком часто его пополнять, можно прибегнуть к помощи $(item)Сокровищницы Ауры$() - улучшенной версии $(item)Кэша Ауры$(), обладающей в три раза большей вместимостью."
    },
    {
      "type": "crafting",
      "text": "Создание $(item)Сокровищницы Ауры$()",
      "recipe": "naturesaura:aura_trove"
    }
  ]
}