{
  "name": "Рюкзаки",
  "icon": "l2backpack:backpack_white",
  "category": "l2backpack:items",
  "sortnum": 1,
  "pages": [
    {
      "type": "patchouli:spotlight",
      "item": "tag:l2backpack:backpacks",
      "text": "Рюкзак хранит предметы внутри, но его нельзя поместить в шалкеровые ящики или другие рюкзаки. Он имеет 16 цветов.$(br2)Изначально он имеет 18 слотов, и вы можете улучшить его с помощью $(l:items/8_ender_pocket)Эндер-кармана$(/l).$(br2)Поддерживает Быстрый Доступ из инвентаря."
    },
    "Features:$(li)This can be put on chest slot (or back slot of Curios), and can be opened via key bind.$(li)$(l:mechanics/inv_access)Quick Inventory Access$(/l)$(li)$(l:mechanics/chest)Load / Dump with Chest$(/l)$(li)$(l:mechanics/quick_insert)Quick Insert$(/l)$(li)$(l:mechanics/exit)Menu Stacking$(/l)$(li)$(l:mechanics/pickup)Recursive Pickup$(/l)$(li)Press ALT to insert as Pickup"
  ]
}