{
  "name": "Драугр некромант",
  "icon": "cataclysm:black_steel_ingot",
  "category": "goety:cataclysm/world/bestiary",
  "pages": [
    {
      "type": "patchouli:text",
      "text": "Эти неживые колдуны когда-то были мудрецами среди воинов, заточивших Маледиктуса, но, как и все остальные, они пали жертвами его проклятия. Но вместо того чтобы оставаться в Морозной Тюрьме, они бродят по холодной тундре в поисках жертв, чтобы пополнить свои ряды."
    },
    {
      "type": "patchouli:entity",
      "entity": "goety_cataclysm:draugr_necromancer",
      "scale": 0.95
    },
    {
      "type": "patchouli:text",
      "text": "Эти некроманты обладают способностью призывать драугров и стрелять призрачными стрелами, которые, кажется, следуют за целью. Как и другие драугры, эти существа не замерзают и не ходят по рыхлому снегу."
    }
  ]
}