{
  "name": "Жезл Блейзджет",
  "sortnum": 5,
  "category": "justdirethings:items",
  "icon": "justdirethings:blazejet_wand",
  "pages": [
    {
      "type": "patchouli:text",
      "text": "Жезл Блейзджет — отличный способ передвижения! Он обладает встроенной способностью воздушного рывка.$(br2)Активируйте эту способность, нажав правую кнопку мыши (или настройте её на экране настроек инструмента), чтобы отбросить вас в направлении, куда вы смотрите."
    },
    {
      "type": "patchouli:text",
      "text": "Более высокие уровни этого жезла позволяют вам перемещаться ещё дальше, что можно настроить с помощью ползунка на экране настроек инструмента.$(br2)Держа его в руке, вы не получите урона от падения. Но убедитесь, что он у вас в руке!$(br2)Этот инструмент обладает способностью к ремонту лавой, поэтому бросьте его в блок источника лавы, чтобы починить."
    },
    {
      "type": "patchouli:crafting",
      "title": "Создание Жезла Блейзджет",
      "recipe": "justdirethings:blazejet_wand"
    }
  ]
}