{
  "name": "Пудинг из сладких ягод",
  "icon": "goetydelight:sweet_berry_pudding",
  "category": "goety:goetydelight/food",
  "pages": [
    {
      "type": "patchouli:text",
      "text": "Бросьте ягоды, эктоплазму и шарики слизи в котёл, чтобы сварить этот шелковисто-гладкий пудинг.$(br)Даёт потребителю:$(br)$(li)5 минут Регенерации II и Питания$(br)Дополнительно увеличивает урон от атаки на 3 и скорость передвижения на 5%."
    },
    {
      "type": "goety:cooking",
      "recipe": "goetydelight:cooking/sweet_berry_pudding"
    }
  ]
}