{
  "name": "Великий Скользень [SM]",
  "icon": "simplymore:great_slither",
  "advancement": "simplymore:great_slither",
  "category": "simplyswords:category_unique_weapons",
  "pages": [
    {
      "type": "patchouli:spotlight",
      "item": "simplymore:great_slither",
      "text": "$(#0BE334)Предмет добавлен в Simply More$(br2)$()Клык ныне покойного великого змея, вырванный мудрецом, который его убил. Великий Скользень излучает тепло, так как по нему всё ещё течёт кровь великого змея. Этот клинок сохраняет магические свойства существа,"
    },
    {
      "type": "patchouli:text",
      "text": "позволяя ему призывать клыки из земли, вводя смертельные токсины по всему телу жертвы. Клинок, кажется, сбрасывает свою оболочку со временем, всегда сохраняя обновлённое, острое лезвие."
    }
  ]
}