{
  "name": "Revvengine [SM]",
  "icon": "simplymore:revvengine",
  "advancement": "simplymore:revvengine",
  "category": "simplyswords:category_unique_weapons",
  "pages": [
    {
      "type": "patchouli:spotlight",
      "item": "simplymore:revvengine",
      "text": "$(#0BE334)Предмет добавлен в Simply More$(br2)$()Двигатель гудит, а из перегревающегося выхлопа вырывается дым — конструктивный недостаток, напоминающий о его прототипном статусе. Revvengine служит модифицированной версией одного из самых распространенных инструментов Общества Стимпанка, бензопилы; наспех сделанной для помощи в"
    },
    {
      "type": "patchouli:text",
      "text": "недавней, неожиданной войне. Он был быстро списан, когда было спроектировано новое, лучшее вооружение, но несколько экспериментальных моделей все еще можно найти сломанными на бывших полях сражений."
    }
  ]
}