{
  "name": "Похититель Душ",
  "icon": "simplyswords:soulstealer",
  "advancement": "simplyswords:soulstealer",
  "category": "simplyswords:category_unique_weapons",
  "pages": [
    {
      "type": "patchouli:spotlight",
      "item": "simplyswords:soulstealer",
      "text": "Похититель Душ — это могущественное и загадочное оружие, которому приписывают способность похищать души своих жертв и искажать их восприятие. Считается, что этот артефакт позволяет не только манипулировать разумом, но и перемещать владельца, окутывая разум врагов туманом и делая их слепыми к его присутствию."
    },
    {
      "type": "patchouli:text",
      "text": "Истинная природа и возможности Похитителя Душ до конца не изучены, ведь это крайне редкое и желанное оружие, которое, по слухам, находится только у самых могущественных и зловещих личностей."
    }
  ]
}