{
  "name": "Редактирование фильтров",
  "icon": "minecraft:writable_book",
  "category": "bloodmagic:demon_will/item_routing",
  "pages": [
    {
      "type": "patchouli:text",
      "text": "Если вы настраиваете большое количество $(thing)фильтров$(), или хотите расширить свои существующие настройки фильтров, просто поместите от двух до 9 фильтров в верстак, чтобы скопировать фильтр из первого слота на все остальные фильтры."
    },
    {
      "type": "bloodmagic:manual_recipe",
      "input1": "bloodmagic:itemrouterfilterexact{Items: [{Slot: 0b, id: \"minecraft:leather\", Count: 1b, tag: {stackSize: 1}}], \"button:blackwhitelist\": 0}",
      "input2": "bloodmagic:itemrouterfilterexact",
      "input9": "bloodmagic:itemrouterfilterexact",
      "output": "bloodmagic:itemrouterfilterexact#3{Items: [{Slot: 0b, id: \"minecraft:leather\", Count: 1b, tag: {stackSize: 1}}], \"button:blackwhitelist\": 0}"
    },
    {
      "type": "patchouli:text",
      "text": "Аналогично, если вы хотите очистить фильтр, поместите его в верстак отдельно, вот так."
    },
    {
      "type": "bloodmagic:manual_recipe",
      "input1": "bloodmagic:itemrouterfilterexact{Items: [{Slot: 0b, id: \"minecraft:leather\", Count: 1b, tag: {stackSize: 1}}], \"button:blackwhitelist\": 0}",
      "input2": "minecraft:air",
      "input9": "minecraft:air",
      "output": "bloodmagic:itemrouterfilterexact"
    }
  ]
}