{
  "name": "Исполнение ритуалов",
  "icon": "goety:dark_altar",
  "category": "goety:rituals",
  "sortnum": 0,
  "priority": true,
  "pages": [
    {
      "type": "patchouli:text",
      "text": "Тёмный алтарь является центральным элементом большинства ритуалов. Прежде всего, алтарь должен быть установлен на $(l:intro/cursed_cage)проклятую клетку$(), а клетка должна быть наполнена энергией душ."
    },
    {
      "type": "patchouli:crafting",
      "recipe": "goety:dark_altar",
      "recipe2": "goety:pedestal"
    },
    {
      "type": "patchouli:text",
      "recipe": "goety:dark_altar_stone",
      "recipe2": "goety:pedestal_stone"
    },
    {
      "type": "patchouli:text",
      "recipe": "goety:dark_altar_deepslate",
      "recipe2": "goety:pedestal_deepslate"
    },
    {
      "type": "patchouli:multiblock",
      "recipe": "goety:dark_altar_nether_brick",
      "recipe2": "goety:pedestal_nether_brick"
    },
    {
      "type": "patchouli:crafting",
      "recipe": "goety:dark_altar_blackstone",
      "recipe2": "goety:pedestal_blackstone"
    },
    {
      "type": "patchouli:crafting",
      "recipe": "goety:dark_altar_end_stone",
      "recipe2": "goety:pedestal_end_stone"
    },
    {
      "type": "patchouli:crafting",
      "recipe": "goety:dark_altar_highrock",
      "recipe2": "goety:pedestal_highrock"
    },
    {
      "type": "patchouli:crafting",
      "recipe": "goety:dark_altar_marble",
      "recipe2": "goety:pedestal_marble"
    },
    {
      "type": "patchouli:text",
      "text": "Используя Тёмный Алтарь, вы можете создать определённый предмет или призвать существо в зависимости от блоков и предметов, окружающих Алтарь. В отличие от других школ магии, эти блоки $(l)не$() должны быть расположены в определённом порядке для работы ритуала. Важно, чтобы определённое количество определённых блоков находилось $(l)внутри$() $(l)радиуса 8 блоков$() Алтаря (по умолчанию). Нажатие правой кнопкой мыши по Тёмному Алтарю с пустой рукой покажет радиус действия, повторное нажатие скроет его."
    },
    {
      "type": "patchouli:text",
      "text": "Чтобы начать ритуал, вы должны сначала заполнить пьедесталы необходимыми предметами $(l)перед$() размещением предмета Алтаря. Когда ритуал будет проходить, Алтарь будет высасывать Энергию Души из Клетки, поэтому лучше убедитесь, что её достаточно, прежде чем проводить Ритуал! Пьедесталы можно использовать для украшения."
    },
    {
      "type": "patchouli:multiblock",
      "multiblock": {
        "pattern": [
          [
            "C"
          ],
          [
            "S"
          ],
          [
            "0"
          ]
        ],
        "mapping": {
          "C": "goety:dark_altar",
          "S": "goety:cursed_cage"
        },
        "symmetrical": true
      },
      "enable_visualize": false
    }
  ]
}