{
  "name": "Прокладывание пути",
  "icon": "simplyswords:runic_tablet",
  "category": "simplyswords:category_rune_etching",
  "pages": [
    {
      "type": "patchouli:spotlight",
      "item": "simplyswords:runic_tablet",
      "title": "Прокладывание пути",
      "text": "Прокладывание пути — это руническая сила, наполняющая оружие владельца $(#bf4117)$(l)эссенцией огня$(). $(br2)Даёт шанс поджечь самого владельца, а также увеличивает его скорость передвижения после каждого успешного удара."
    },
    {
      "type": "patchouli:text",
      "text": "Эта руна может быть полезна в сражениях против врагов, полагающихся на скорость и мобильность, ведь повышение скорости позволяет обойти их и перехитрить. $(br2)Эффект поджигания может стать недостатком для персонажей с низкой защитой, но дополнительная скорость способна компенсировать этот риск в определённых ситуациях."
    }
  ]
}